annt/__init__.py
annt/box.py
annt/color.py
annt/converter.py
annt/loader.py
annt/main.py
annt/polygon.py
annt/utils.py
test/__init__.py
test/test.py
test/test_box.py
test/test_converter.py
test/test_loader.py
test/test_polygon.py
annt-0.0.7.dist-info/LICENCE
annt-0.0.7.dist-info/METADATA
annt-0.0.7.dist-info/WHEEL
annt-0.0.7.dist-info/top_level.txt
annt-0.0.7.dist-info/RECORD
