Metadata-Version: 2.1
Name: annt
Version: 0.0.7
Summary: annt: Simple annotation tools for object detection task.
Home-page: https://mikebird28.hatenablog.jp/
Author: Keisuke Miura
Author-email: hello.mikeneko@gmail.com
License: UNKNOWN
Platform: UNKNOWN
Classifier: Development Status :: 2 - Pre-Alpha
Classifier: License :: OSI Approved :: MIT License
Classifier: Programming Language :: Python :: 3.5
Classifier: Programming Language :: Python :: 3.6
Classifier: Programming Language :: Python :: 3.7
Classifier: Programming Language :: Python :: 3.8
Classifier: Programming Language :: Python :: 3.9
